test_paket/__init__.py
test_paket/modul1.py
test_paket/modul2.py
demo_project_28_03_2025-0.0.1.dist-info/METADATA
demo_project_28_03_2025-0.0.1.dist-info/WHEEL
demo_project_28_03_2025-0.0.1.dist-info/top_level.txt
demo_project_28_03_2025-0.0.1.dist-info/RECORD
